.gitignore
LICENSE
MANIFEST.in
README.md
setup.py
imview/__init__.py
imview/color_hs.py
imview/color_hs_mpl.py
imview/fig2jpg.sh
imview/hs_multi.py
imview/hs_multi.sh
imview/imviewer.py
imview/inpaint.py
imview/iv.py
imview/review_img.py
imview/stack_view.py
imview.egg-info/PKG-INFO
imview.egg-info/SOURCES.txt
imview.egg-info/dependency_links.txt
imview.egg-info/requires.txt
imview.egg-info/top_level.txt
imview/lib/__init__.py
imview/lib/gmtColormap.py
imview/lib/pltlib.py
imview/lib/rainbow.cpt