Metadata-Version: 2.1
Name: imview
Version: 0.4.0
Summary: Image viewers for geospatial data
Home-page: https://github.com/dshean/imview
Author: David Shean
Author-email: dshean@gmail.com
License: MIT
License-File: LICENSE
Requires-Dist: numpy
Requires-Dist: gdal
Requires-Dist: matplotlib
Requires-Dist: pygeotools
Requires-Dist: matplotlib-scalebar
Requires-Dist: matplotlib-colorbar
